barbucket/__init__.py
barbucket/app/cli.py
barbucket/app/logging_preparator.py
barbucket/app/main.py
barbucket-0.3.dist-info/LICENSE.md
barbucket-0.3.dist-info/METADATA
barbucket-0.3.dist-info/WHEEL
barbucket-0.3.dist-info/entry_points.txt
barbucket-0.3.dist-info/top_level.txt
barbucket-0.3.dist-info/RECORD
