Metadata-Version: 2.1
Name: barbucket
Version: 0.3
Summary: My package description
Home-page: https://github.com/croidzen/barbucket
Author: Martin Creutzenberg
Author-email: reach_me_on_github@invalid.com
License: MIT License
Project-URL: Documentation, https://barbucket.readthedocs.io/
Platform: UNKNOWN
Classifier: Development Status :: 4 - Beta
Classifier: Environment :: Console
Classifier: Intended Audience :: Developers
Classifier: Intended Audience :: Science/Research
Classifier: License :: OSI Approved :: MIT License
Classifier: Operating System :: POSIX :: Linux
Classifier: Operating System :: MacOS
Classifier: Programming Language :: Python :: 3
Classifier: Topic :: Database
Classifier: Topic :: Office/Business :: Financial :: Investment
Classifier: Topic :: Scientific/Engineering :: Information Analysis
Requires-Python: >=3.10
License-File: LICENSE.md
Requires-Dist: beautifulsoup4
Requires-Dist: click
Requires-Dist: enlighten
Requires-Dist: ib-insync
Requires-Dist: numpy
Requires-Dist: pandas
Requires-Dist: psycopg2-binary
Requires-Dist: requests
Requires-Dist: sqlalchemy
Requires-Dist: trading-calendars
